COPYING
MANIFEST.in
README.rst
buildout.cfg
requirements.txt
setup.py
version.txt
bob/__init__.py
bob.hobpad2.chapter20.egg-info/PKG-INFO
bob.hobpad2.chapter20.egg-info/SOURCES.txt
bob.hobpad2.chapter20.egg-info/dependency_links.txt
bob.hobpad2.chapter20.egg-info/requires.txt
bob.hobpad2.chapter20.egg-info/top_level.txt
bob/hobpad2/__init__.py
bob/hobpad2/chapter20/__init__.py
bob/hobpad2/chapter20/test.py
doc/conf.py
doc/index.rst
doc/img/favicon.ico
doc/img/logo.png